{"ok": true, "comments": [{"t": "幼い頃から毒親に育てられたにしては、まともな善悪判断ができて良かった", "l": 3200, "r": 0, "s": 0}, {"t": "最後にゃ自力で立ち直ったのが良い 姉弟の人生が実りあるものでありますように", "l": 1700, "r": 0, "s": 0}, {"t": "弟さんと一緒に幸せになってください。そんな親と離れられたのはその一歩です。", "l": 955, "r": 0, "s": 0}, {"t": "養護施設に入れて本当に良かった！", "l": 437, "r": 0, "s": 0}, {"t": "教 育 の 大 事 さ", "l": 278, "r": 0, "s": 0}, {"t": "いいお姉ちゃんだなあ😢", "l": 175, "r": 0, "s": 0}, {"t": "どんなに幼くても、善悪の区別はつくよね。さぞかし嫌だったでしょうね。でも、やらなかったら母親に叱られるだろうし、食べられないもんね。 逃げるチャンスと弟を連れて…毒親に育てられて、前科つく事になっても、弟に教えなかったのは、それが悪いことと、理解してた証拠。施設の人達が良い人達だったから、万引きやめられた。貴女の良心は正しく機能してますよ。過去を忘れ、弟さんと幸せになって下さいね。😊", "l": 157, "r": 0, "s": 0}, {"t": "悲惨な母親のもとで生まれだ姉弟さん 児童福祉施設を卒業した子供たちの多くが音信不通になるらしい どうか彼らを支える制度ができてほしい", "l": 127, "r": 0, "s": 0}, {"t": "子供は親を選べない。このお姉ちゃんは弟思いで、そこが尚更泣けてくる。母親から逃れられて良かった。", "l": 117, "r": 0, "s": 0}, {"t": "子供は親を選べない 毒親に育てられる子供を不憫に思う", "l": 93, "r": 0, "s": 0}, {"t": "子どもは親にすごく影響されるし、それが正しいと思ってしまうから難しいよね。", "l": 48, "r": 0, "s": 0}, {"t": "万引きで捕まると、その記録はずーっと残るよ。放火犯の裁判を傍聴した時に、子供の頃の万引きの事とか、GAME好きとかの趣味嗜好等、いろいろ育ってきた環境を傍聴席で聞かされて、辱め受けてからの裁判って普通の人だときついなぁと思ったよ。だから、万引きなんかしちゃ駄目だよ。", "l": 34, "r": 0, "s": 0}, {"t": "毒親は何処にでもいる。 自分で変えて行くしかない。", "l": 31, "r": 0, "s": 0}, {"t": "えぐいやろ😭", "l": 25, "r": 0, "s": 0}, {"t": "親がもともと万引きを教えたりしない優しい親だったら元から良いことや、悪いことが、判別できてたら、でも施設とかで、幸せになれてよかった", "l": 21, "r": 0, "s": 0}, {"t": "子供は親を選ぶことが出来ないってよく言われた。", "l": 20, "r": 0, "s": 0}, {"t": "弟に盗みを教えなかったって…この子にはちゃんと良心があって、それを毒親に捻じ曲げられてたことがよくわかる言葉だね。逃げられて良かった…", "l": 19, "r": 0, "s": 0}, {"t": "盗癖は治らないがこの子は生きる手段としての盗みだったので生活出来るようになったら止めれた", "l": 18, "r": 0, "s": 0}, {"t": "でもやってることが犯罪なんだよなー", "l": 11, "r": 1, "s": 0}, {"t": "毒親すぎる‼️", "l": 11, "r": 0, "s": 0}, {"t": "言ってることに間違いはないけど、君の書き込みはずれてることに気がつかないかな？", "l": 9, "r": 1, "s": 0}, {"t": "厳しくしつけるのが、万びきってどうよ", "l": 9, "r": 0, "s": 0}, {"t": "頑張っていきましょう❤", "l": 9, "r": 0, "s": 0}, {"t": "少年法はこういう怪我人の居ない窃盗（万引き）だけ適応されるべきなのだ。 殺人事件や暴行事件は、未成年でも成人と同じ罰を与えよ。", "l": 8, "r": 0, "s": 0}, {"t": "真面目に生きてればいい事があるよ〜と今の政権見てると言えんな。😢", "l": 8, "r": 0, "s": 0}, {"t": "これ社会問題やろ", "l": 8, "r": 0, "s": 0}, {"t": "いやまず万引きなんて犯罪の塊やで！何故子供にあかんことを教育させとんねん！", "l": 6, "r": 0, "s": 0}, {"t": "「子は親を選んで生まれてくる」とか言ってくる人は、こういう子供たちの話を聞いてもまだ言えるのだろうか。", "l": 5, "r": 0, "s": 0}, {"t": "こんな子供達今でもいるのかな こども家庭庁ってこういうの視聴してますか？", "l": 5, "r": 0, "s": 0}, {"t": "いい話っぽくしてるけど養護施設入ったあともしてるとか終わっとるやろ", "l": 4, "r": 0, "s": 0}, {"t": "万引き家族のリアル版", "l": 3, "r": 0, "s": 0}, {"t": "婦警さんの回顧談でしょうか。", "l": 3, "r": 0, "s": 0}, {"t": "万引きの癖って中々抜けないんですよ ただこの人の場合はまともな母親に養育されていたわけではないし生きていくために幼少からやらざるを得ない環境にいたことを鑑みたら終わっているとは言えない部分がある 勿論やってはダメなことだけどこういうケースで癖がついてしまった子はかなりの確率で大人になってもズルズルとやってしまう…… タバコや大麻の依存性何かと通ずる部分があります やめれただけでもかなり凄いことなんです", "l": 3, "r": 1, "s": 0}, {"t": "父親は…?", "l": 3, "r": 0, "s": 0}, {"t": "何が妹バージョンでこんな話し見たなー😅", "l": 3, "r": 0, "s": 0}, {"t": "その更生した話やん 話の内容も理解できねえのかよ", "l": 3, "r": 1, "s": 0}, {"t": "捕まるのは母親でしょう。 父親はどうしたの？ 戸籍に父親の名はなし？ 調べて量共に刑務所行きだ。 子供たちは被害者。", "l": 2, "r": 0, "s": 0}, {"t": "確かに、でも万引きがだめと教えてもらってるのかにもよるかも", "l": 2, "r": 1, "s": 0}, {"t": "万引きしてたら 碌なことないよ", "l": 2, "r": 0, "s": 0}, {"t": "いい話…なのかなぁ？", "l": 2, "r": 0, "s": 0}, {"t": "盗み癖って一度付くと中々抜けないんですよ この子の環境的にもやらなきゃ生きていけないという強迫概念が少なからずあっただろうし…… こういうケースの多くは大人になってもズルズルとやってしまう程でタバコや違法薬物の依存性と通ずる部分があります なので社会に出る前に辞めることが出来たのは本当に凄いことなんです なので手遅れと言うのは違うかと……", "l": 2, "r": 1, "s": 0}, {"t": "毒親のせいにするなよ どんな環境でも立派に育つ人間はいるんだよ。", "l": 2, "r": 0, "s": 0}, {"t": "いやいつでも万引き出来るやつなんだから捕まえろよ", "l": 2, "r": 0, "s": 0}, {"t": "なんで施設入ってるのに万引きするの？", "l": 2, "r": 0, "s": 0}, {"t": "クセじゃない？", "l": 2, "r": 1, "s": 0}, {"t": "盗み癖ですね 盗み癖は中々抜けないんですよ 特にこの子みたいに母親がやるように言われて生きてきた子はそうしないと生きていけないという強迫概念がありますし……", "l": 2, "r": 1, "s": 0}, {"t": "良いことしたみたいなオチで草", "l": 1, "r": 0, "s": 0}, {"t": "日本中の施設を大臣自ら巡って親を締め付けろ", "l": 1, "r": 1, "s": 0}, {"t": "なんで貧乏なのに子供産んでんだよ", "l": 1, "r": 0, "s": 0}, {"t": "母親にはメッチャクチャ苦しいﾀﾋに方でイッてくれ", "l": 1, "r": 0, "s": 0}, {"t": "ゲームでやるんだったら面白そう", "l": 1, "r": 0, "s": 0}, {"t": "子供も三人は自立して、今は3男の１８歳がいる。 年の離れたお兄ちゃんがいるけど、良いなら家においで。 もちろん、弟さんも一緒にね❤", "l": 1, "r": 0, "s": 0}, {"t": "確かにそんな人間は居るかもしれないけれど全員がそうなる訳じゃないからな", "l": 1, "r": 1, "s": 0}, {"t": "盗み癖って中々抜けないんですよ タバコや違法薬物の依存性のようなものでこういうケースの子はカウンセリングなどを受けても大人になってもずぶやってしまうパターンが多いほどです……", "l": 1, "r": 1, "s": 0}, {"t": "私見だけど「前世でおなじことをさせた」罪だと思ってる 自分がいじめられていた時もそう思ってた もう同じことはしないと決めたらいじめも修まった 生きてる間にうまれ変わることはできるとも思ってます", "l": 0, "r": 1, "s": 0}, {"t": "大丈夫養護施設の職員万引き謝りに行くの慣れてるから😂自分の意思でやめれてえらい", "l": 0, "r": 0, "s": 0}, {"t": "責任を持って子どもを育ててほしい", "l": 0, "r": 0, "s": 0}, {"t": "万引きなんてたとえ母親の言う事でも、聞かなくていい", "l": 0, "r": 0, "s": 0}, {"t": "親の教育は大事", "l": 0, "r": 0, "s": 0}, {"t": "愛を与えられたら健全に育つのだなあと考えさせられるお話しです。 犯罪を犯す全ての人が愛された経験がない人というわけではないでしょうが…", "l": 0, "r": 0, "s": 0}, {"t": "お天道様が見ていると思って下さい。正直に生きてたら必ずいいことがある。", "l": 0, "r": 0, "s": 0}, {"t": "てかそういう万引き毒親はお金がないんだろうねぇ", "l": 0, "r": 0, "s": 0}, {"t": "万引きをしろ、と言う親なんて、親じゃ無い。 収入が少なかったら、仕事が終わったら、内職してでも食費の足しにするのが、母親です。 施設に入って、まともな生活が出来る様になって良かった。 万引きするのは簡単だけど、やってはいけないと思ってくれたのが嬉しかったです。", "l": 0, "r": 0, "s": 0}, {"t": "辛い思いしてたね", "l": 0, "r": 0, "s": 0}, {"t": "ほんまかよ", "l": 0, "r": 0, "s": 0}, {"t": "もう一度子育てしたいな。 お金と体力が有れば。", "l": 0, "r": 0, "s": 0}, {"t": "警察さん、この人です！w", "l": 0, "r": 0, "s": 0}, {"t": "こりやあこまった", "l": 0, "r": 0, "s": 0}, {"t": "ほぼ同じ話で弟が妹のバージョン見たんだが？", "l": 0, "r": 0, "s": 0}, {"t": "警察署行け", "l": 0, "r": 0, "s": 0}, {"t": "全部余裕だった", "l": 0, "r": 0, "s": 0}, {"t": "親ガチャ失敗", "l": 0, "r": 0, "s": 0}, {"t": "お父さんは居ないのかな、", "l": 0, "r": 0, "s": 0}, {"t": "誰だよ母親に万引き教えたやつ", "l": 0, "r": 0, "s": 0}, {"t": "これを「親ガチャ」と言うのかな？", "l": 0, "r": 0, "s": 0}, {"t": "根はいい", "l": 0, "r": 0, "s": 0}, {"t": "万引きが主な原因で店は潰れるんだ。真面目に生きている人を地獄に落としたんだ。ちゃんと償って生きていくんだよ", "l": 0, "r": 0, "s": 0}, {"t": "弟にさせない程度に善悪の認識ができてるのに施設入ってもやってるのはもう手遅れだろ", "l": 0, "r": 0, "s": 0}, {"t": "パクリやん", "l": 0, "r": 0, "s": 0}, {"t": "施設行ってから万引きしたことは意味わからんが", "l": 0, "r": 0, "s": 1}], "n_total": 84}