{"ok": true, "comments": [{"t": "すごいです。再会して2人で幸せをつかむなんて🎉お幸せに😊", "l": 1400, "r": 0, "s": 0}, {"t": "運命ですね。素敵です❤", "l": 854, "r": 0, "s": 0}, {"t": "いい話ご馳走様でした❤ いつまでもお幸せに……", "l": 381, "r": 0, "s": 0}, {"t": "良い話ですね〜結婚する何て凄い", "l": 273, "r": 0, "s": 0}, {"t": "「空の上で再会」 娘の表現が素敵", "l": 190, "r": 0, "s": 0}, {"t": "二人に恋人フリーだったのも縁があったのですね💕", "l": 163, "r": 0, "s": 0}, {"t": "縁があれば、何年経とうが、場所がドコだろうが、必ず引き寄せ合うらしいですね😊", "l": 127, "r": 0, "s": 0}, {"t": "AIに頭が緩い奴が感動できる物語作ってくださいって指示出したら作ってくれそう", "l": 47, "r": 0, "s": 0}, {"t": "見事なまでのDT妄想", "l": 46, "r": 0, "s": 0}, {"t": "これは流石に無理がある", "l": 32, "r": 0, "s": 1}, {"t": "あんま妄想すんなって", "l": 17, "r": 0, "s": 0}, {"t": "こうゆうことが現実に起きたらいいよなー", "l": 15, "r": 0, "s": 0}, {"t": "夢もしっかり叶えて、凄い", "l": 14, "r": 1, "s": 0}, {"t": "んなわけねーだろwってつっこんだけど、コメント欄の信じる人の多いのにびびったわ。", "l": 12, "r": 1, "s": 0}, {"t": "幸せになりやがれください!!", "l": 11, "r": 0, "s": 0}, {"t": "幸せに成り上がれ！", "l": 11, "r": 0, "s": 0}, {"t": "縁が結ぶ素敵な出会い。", "l": 10, "r": 0, "s": 0}, {"t": "幼い頃のツーショット写真 持ち歩いてたんだ", "l": 9, "r": 0, "s": 0}, {"t": "このての話しが最近多い", "l": 9, "r": 0, "s": 0}, {"t": "それぞれが叶えた夢の中での『出逢い』 素晴らしい。", "l": 9, "r": 0, "s": 0}, {"t": "フィクションてわかんないのか、フィクションでも良いと思ってるのかどっちすか？", "l": 8, "r": 1, "s": 0}, {"t": "幼なじみが近くにいる時になぜか写真が落ちるというまるで計算されたかのようなタイミング", "l": 8, "r": 0, "s": 0}, {"t": "いい話ですが、私にはなかなか縁がない。 とにかく、おめでとう、お幸せに👏🆗💯 m(_ _)m", "l": 8, "r": 0, "s": 0}, {"t": "最高のハプニング❤ 感動です!", "l": 7, "r": 0, "s": 0}, {"t": "手帳から写真・・の話が多いね。 「小さな頃の好きな子の写真」を手帳に入れている奴見たことない。それも落ちそうな所に保管。？？？ 誰か手帳に「小さな頃の好きな子の写真」を入れている人知ってますか？？", "l": 7, "r": 0, "s": 0}, {"t": "ロマンチック❤", "l": 7, "r": 0, "s": 0}, {"t": "んな話はまずないw", "l": 6, "r": 0, "s": 0}, {"t": "てか、大事な写真なのにそんなとこにしまってるのほんと草", "l": 6, "r": 0, "s": 0}, {"t": "こんな話は有り得ない！有って欲しいけど。", "l": 6, "r": 0, "s": 0}, {"t": "素敵だぁ！😆👍👍", "l": 6, "r": 0, "s": 0}, {"t": "@memento-mori-e4k フィクションかどうかの所に議論する意味あるか？このエピソードに対する感想言ってるだけだろ。", "l": 5, "r": 1, "s": 0}, {"t": "運命ねぇ。 仕事しよ…", "l": 5, "r": 0, "s": 0}, {"t": "素敵", "l": 5, "r": 0, "s": 0}, {"t": "これは、ウソくさ(笑)", "l": 5, "r": 0, "s": 0}, {"t": "ガキの頃の写真を後生大事に持ち歩いてる方が逆に気持ち悪いわ😂 DTの妄想恐るべし😂", "l": 5, "r": 0, "s": 0}, {"t": "幼い頃の写真を毎日持ってたのね。", "l": 5, "r": 0, "s": 0}, {"t": "もうちょっと脚本がんばってほしかったよね〜〜😂😂", "l": 5, "r": 1, "s": 1}, {"t": "彼女はCAに、彼氏は絵空事を描くのが夢やったんやろ！？そうやと言うてくれー！", "l": 5, "r": 0, "s": 0}, {"t": "写真が大活躍やん", "l": 5, "r": 0, "s": 0}, {"t": "本気かお前ら", "l": 4, "r": 0, "s": 0}, {"t": "幼馴染の写真もちあるかへんやろ", "l": 4, "r": 0, "s": 0}, {"t": "幼馴染みとの再会出来て、お互いに初恋だったかな⁉相思相愛で、二人の歴史の1ページだね!!❤❤❤❤❤", "l": 4, "r": 0, "s": 0}, {"t": "この手の話しって、だいたい昔の写真を常に手元に持っててタイミングどんぴしゃで落とすよね笑", "l": 3, "r": 0, "s": 0}, {"t": "という夢を見た", "l": 3, "r": 0, "s": 0}, {"t": "衝撃的な幼馴染との再会❤", "l": 3, "r": 0, "s": 0}, {"t": "みーんなすぐ結婚する", "l": 3, "r": 0, "s": 0}, {"t": "写真持ち歩いてるんだぁ😊 …🤔", "l": 3, "r": 0, "s": 0}, {"t": "ca、看護婦、保険屋、 浮気しなきゃいいけどな、、、", "l": 3, "r": 0, "s": 0}, {"t": "@medamaoyaji7663 逆張り寒い", "l": 2, "r": 1, "s": 0}, {"t": "娘「んな事あるわけねぇだろぉ！！」", "l": 2, "r": 0, "s": 0}, {"t": "ファミレステーブル別で草", "l": 2, "r": 0, "s": 0}, {"t": "運命的な出会いですね。 お幸せに", "l": 2, "r": 0, "s": 0}, {"t": "ええエモすぎる", "l": 2, "r": 0, "s": 0}, {"t": "確かにロマンチック", "l": 2, "r": 0, "s": 0}, {"t": "娘さんの表現が素敵過ぎる！", "l": 1, "r": 0, "s": 0}, {"t": "娘ちゃんの言うとうりロマンチックすぎて羨ましいすぎる😭😭", "l": 1, "r": 0, "s": 0}, {"t": "フリーのイラストに安い脚本", "l": 1, "r": 1, "s": 1}, {"t": "娘さんの言うように空の上で 再会なんてロマンチックですね～😊", "l": 1, "r": 0, "s": 0}, {"t": "娘「空の上で再会なんてロマンチック」 父「そうだろ！〇〇はJAL産だからな！」", "l": 1, "r": 0, "s": 0}, {"t": "引っ越し繰り返して、幼なじみとの縁が全くないから異性の幼なじみがいる人って羨ましい", "l": 1, "r": 0, "s": 0}, {"t": "どっちの夢が先だったんだろう？ 「CAになるの」「じゃあ俺は世界を飛び回る仕事する」の方を推す", "l": 1, "r": 0, "s": 0}, {"t": "脳内妄想おつwwww", "l": 1, "r": 0, "s": 0}, {"t": "無駄なことは1つもないってことだね。 もし、オジサンに怒鳴られなければ泣き顔になることも、その顔で思い出すこともなかった。", "l": 1, "r": 0, "s": 0}, {"t": "飛行機でじゃなくて、空の上ってのが素敵", "l": 1, "r": 0, "s": 0}, {"t": "っていう夢を見たんだ", "l": 1, "r": 0, "s": 0}, {"t": "なんでこういう 良い奴らって先に結婚してた的なオチないん。 すげーキュンとくるわ", "l": 1, "r": 0, "s": 1}, {"t": "こういうの見ると結婚相手ってなんだかんだ強い運命的なものを持ってんのかなぁって思っちゃわないよね", "l": 1, "r": 0, "s": 0}, {"t": "まず幼馴染との写真が必要な時点で詰んだ", "l": 1, "r": 0, "s": 0}, {"t": "妄想でも面白いからいいんやで", "l": 1, "r": 1, "s": 0}, {"t": "良かったねェ！ 本当に、自分の事の様に嬉しい、お幸せに！", "l": 1, "r": 0, "s": 0}, {"t": "絶対に【運命の赤い糸】で繋がっていたんです", "l": 1, "r": 0, "s": 0}, {"t": "末永く幸せになりやがれくださいｗ", "l": 1, "r": 0, "s": 0}, {"t": "ってゆー夢でした！とかじゃないのかーー(´；ω；｀)うらやましーなードラマだなー、、お幸せに！！", "l": 1, "r": 0, "s": 0}, {"t": "映画化映画化😊", "l": 1, "r": 0, "s": 0}, {"t": "妄想癖すごいな笑", "l": 1, "r": 0, "s": 0}, {"t": "赤い糸", "l": 0, "r": 1, "s": 0}, {"t": "出来すぎて冷めるね", "l": 0, "r": 1, "s": 0}, {"t": "娘の棒読みがクソ可愛い😂", "l": 0, "r": 0, "s": 0}, {"t": "いい話すぎて泣く", "l": 0, "r": 0, "s": 0}, {"t": "20年会ってないのに見覚えのあるって表現がもう運命すぎる！", "l": 0, "r": 0, "s": 0}], "n_total": 90}