{"ok": true, "comments": [{"t": "未来ではなく、あの世何じゃないかなとおもうが。", "l": 460, "r": 0, "s": 0}, {"t": "きよみちゃんがこっちに来るな！と言った途端把握した あの世やと", "l": 343, "r": 0, "s": 0}, {"t": "多分あの世だな", "l": 109, "r": 0, "s": 0}, {"t": "きっときよみちゃんが天国から見守っているんだね😢", "l": 100, "r": 0, "s": 0}, {"t": "頭が？？でいっぱいになった", "l": 92, "r": 0, "s": 0}, {"t": "自分自身が最高の友人、助けるのも自分自身。最高です。いいですね。", "l": 75, "r": 0, "s": 0}, {"t": "きよみちゃんはあっちの岸に渡っちゃったんだね イッチ追い返されてよかったね", "l": 40, "r": 0, "s": 0}, {"t": "まさかのそっち行ったらあの世行きか", "l": 35, "r": 0, "s": 0}, {"t": "意味わからんと思ってコメ見たら俺だけじゃなくて良かった", "l": 34, "r": 0, "s": 1}, {"t": "２ちゃんねるのまとめで読んで、何か泣きそうになった記憶があります。興味のある方はそちらも是非。", "l": 28, "r": 0, "s": 0}, {"t": "麻酔で意識が薄れるなんて事はありません。匂いの記憶もなく一瞬で意識が無くなります。全身麻酔舐めんなよ。", "l": 15, "r": 0, "s": 0}, {"t": "なんで荒らしって荒らすんだろう 現実で構って貰えないから悲しくてやってるのかな", "l": 14, "r": 1, "s": 0}, {"t": "覚えていなかったら, そのままきよみちゃんのところまで駆け寄っててあの世行きだったかもね.", "l": 14, "r": 0, "s": 0}, {"t": "完治ではなく寛解では", "l": 13, "r": 0, "s": 0}, {"t": "と言う事はきよみちゃんはもうコチラには居ない…と？", "l": 12, "r": 0, "s": 0}, {"t": "いきなり末期ガンで、完治､､。 凄いな。", "l": 11, "r": 0, "s": 0}, {"t": "意味不明", "l": 10, "r": 0, "s": 1}, {"t": "凄い❤", "l": 9, "r": 0, "s": 0}, {"t": "こっちに来ちゃダメってきよみちゃんあの世にいて言ってるのかな？", "l": 9, "r": 0, "s": 0}, {"t": "きよみちゃんは魔法使いだったのかな？", "l": 8, "r": 0, "s": 0}, {"t": "意味わからない😥", "l": 8, "r": 0, "s": 0}, {"t": "全然違う話になってるよね😂", "l": 7, "r": 1, "s": 0}, {"t": "​ @としぞお 急にどうしたの？", "l": 6, "r": 1, "s": 0}, {"t": "​ @としぞお これって上の人関係なくね？", "l": 6, "r": 1, "s": 0}, {"t": "この嵐よく見るけど初めて殺意湧いた", "l": 5, "r": 1, "s": 0}, {"t": "最初の方は、同じだけど、入院の所から、別の話になっている。", "l": 5, "r": 1, "s": 0}, {"t": "全身麻酔は夢見ません。", "l": 5, "r": 1, "s": 0}, {"t": "麻酔で夢は見ません。", "l": 5, "r": 0, "s": 0}, {"t": "きよみちゃんは未来から来た32歳の自分自身かと思ったら別人かよ😅", "l": 4, "r": 0, "s": 0}, {"t": "意味不明、きよみちゃんが誰だったの？ ３２歳で亡くなられた人なのだと思うけど、どう言った関係なのかしら？ 何らかの関係がなければ生きられなかったのでは??", "l": 4, "r": 0, "s": 1}, {"t": "完治ではなく寛解です", "l": 4, "r": 0, "s": 0}, {"t": "私が話し終わったら意識は無くなります。 確かにその通りだった！", "l": 4, "r": 1, "s": 0}, {"t": "アホすぎてよく分からんかったわ きよみちゃん変な奴だと思ってた", "l": 3, "r": 1, "s": 0}, {"t": "ごめん、わからんからコメ見て納得した", "l": 3, "r": 0, "s": 0}, {"t": "なんか泣ける(´；ω；｀)", "l": 3, "r": 0, "s": 0}, {"t": "私も きよみ っていう名前です😂", "l": 3, "r": 0, "s": 0}, {"t": "きよみちゃんは過去から来たのではないか？それなら生年月日から計算したら32歳になるからだ", "l": 2, "r": 0, "s": 0}, {"t": "俺も麻酔経験者だけど個人差ありますよ？", "l": 2, "r": 1, "s": 0}, {"t": "いつも思うんだが命の恩人はきよみちゃんじゃなくて医者な？", "l": 2, "r": 0, "s": 0}, {"t": "イッチさんが子供の時に会った時点できよみちゃんは既に亡くなってた😱😱😱", "l": 1, "r": 1, "s": 0}, {"t": "それな！ あの場所があの世と幽世を仕切る境界線 おそらく、条件付きで幽世と繫がる場所なんだろう あのまま、清美ちゃんの側に歩いていたら、助からなかったんだと思う", "l": 1, "r": 1, "s": 0}, {"t": "他の、人には見えない友達", "l": 1, "r": 0, "s": 0}, {"t": "自分自身じゃないのか？ 名前は違うが", "l": 1, "r": 0, "s": 0}, {"t": "意味がわからん 続編作れ", "l": 1, "r": 0, "s": 1}, {"t": "秒で起こされるよな。同じ病気で手術した人達がXでタイムスリップと呼んでいた。 そして痛み止め飲んでたから6時間経つのを時計とにらめっこしながら痛みに耐える。", "l": 1, "r": 1, "s": 0}, {"t": "確か夢ってのはその人の記憶の整理だったはず。だからぐっすり眠ってる人ほど夢は見ないんだって", "l": 1, "r": 1, "s": 0}, {"t": "まぁきよみは先に死んでたのだけよね、分かるとこ", "l": 1, "r": 1, "s": 0}, {"t": "？", "l": 1, "r": 0, "s": 0}, {"t": "子供の頃に会ったきよみちゃんは既に亡くなっててイッチさんが手術中の臨死体験できよみちゃんが現世に戻してくれたんだね😭😭😭", "l": 0, "r": 0, "s": 0}, {"t": "突発的に生死さまよった人はこういう夢見るらしい", "l": 0, "r": 0, "s": 0}, {"t": "未来も、あの世も、別次元も 何でもありよね、全部自分の意識の産物。 この世はバーチャル。", "l": 0, "r": 0, "s": 0}, {"t": "あの世かな？ アンビリバボーの『ゆうちゃん』思い出した。", "l": 0, "r": 0, "s": 0}, {"t": "きよみちゃんとぶるぶるちゃんなら後半が違い過ぎる あ～でも私も20代前半の頃32歳の私に話かけられた事はある (脳内だけど😂)新婚で幸福な私からドン底の私へ", "l": 0, "r": 0, "s": 0}, {"t": "私幼稚園できよみちゃんいる！", "l": 0, "r": 0, "s": 0}, {"t": "きよみちゃんは、もう。", "l": 0, "r": 0, "s": 0}, {"t": "世にも奇妙な物語の未来同窓会的なやつ？", "l": 0, "r": 0, "s": 0}, {"t": "私麻酔で夢見たな〜", "l": 0, "r": 0, "s": 0}, {"t": "きよみちゃんって 未来の自分？？", "l": 0, "r": 0, "s": 0}, {"t": "きよみちゃん ありがとう", "l": 0, "r": 0, "s": 0}, {"t": "きよみちゃん未来から来たならがん検査こまめに受けろって教えてあげてよ", "l": 0, "r": 0, "s": 0}, {"t": "ふうらかふか", "l": 0, "r": 0, "s": 0}, {"t": "どういう事？ あっちにいくと小３に戻ってしまうとか？", "l": 0, "r": 0, "s": 0}, {"t": "そちにわいたらだめしぬていみみ？", "l": 0, "r": 0, "s": 0}, {"t": "二重人格？？？的な？？？ きよちゃんはもう一人の自分の？？？ 自身の分身？？？", "l": 0, "r": 0, "s": 0}, {"t": "きよみちゃんは亡くなってたのかな？", "l": 0, "r": 0, "s": 0}, {"t": "幽霊だったの？", "l": 0, "r": 0, "s": 0}, {"t": "そうですね。 失礼しました。 1/5程度には夢を見る方がいて、特に若い方に多いそうです。", "l": 0, "r": 1, "s": 0}, {"t": "で、32歳のきよみちゃんは、どうしてるん？", "l": 0, "r": 0, "s": 0}, {"t": "どうゆうこと？わからん", "l": 0, "r": 0, "s": 0}, {"t": "ちょっと意味が分からない", "l": 0, "r": 0, "s": 0}, {"t": "説得力薄い", "l": 0, "r": 0, "s": 0}, {"t": "ん～～🤔でもいい😭", "l": 0, "r": 0, "s": 0}], "n_total": 72}