{"ok": true, "comments": [{"t": "たくさん食べて 良く運動して 健康に育って よきよき☺️", "l": 935, "r": 0, "s": 0}, {"t": "この話､好き😄", "l": 503, "r": 0, "s": 0}, {"t": "超絶元気な子！！", "l": 238, "r": 0, "s": 0}, {"t": "これは生後6か月で腹筋が浮き出しますわ", "l": 232, "r": 0, "s": 0}, {"t": "まさか、前世の記憶なのか？ 前世の赤ちゃん『やはり筋肉！筋肉は全て解決する！』", "l": 152, "r": 0, "s": 0}, {"t": "すごい😂赤ちゃんの頃から筋トレが欠かさない子なんですね可愛い❣️", "l": 129, "r": 0, "s": 0}, {"t": "生まれついてのアスリートですな(笑)", "l": 120, "r": 0, "s": 0}, {"t": "武井壮さんで再生された❤笑 健康で元気な子で良かった😊", "l": 87, "r": 0, "s": 0}, {"t": "可愛い〜🥹", "l": 65, "r": 0, "s": 0}, {"t": "私も赤ちゃんの頃痩せていたらしくて心配した母親が健診で相談したら ｢見て、あなたの娘さんすごくよく動いてるでしょ。こんなに運動してるんだもん太るのが難しいよ｣って言われたらしい。 小学校低学年までは運動神経もすごく良かったけど、引きこもってからは段差なくても転ぶ。", "l": 47, "r": 0, "s": 0}, {"t": "次男は夜中に運動してたから太らなかったのか、なるほど", "l": 35, "r": 0, "s": 0}, {"t": "筋肉エリート‥", "l": 28, "r": 0, "s": 0}, {"t": "この歳だともはや才能", "l": 24, "r": 1, "s": 0}, {"t": "とてもほっこりしますよね😊", "l": 17, "r": 1, "s": 0}, {"t": "赤ちゃんでスクワット早いのすごいwww", "l": 15, "r": 0, "s": 0}, {"t": "2！赤ちゃん可愛い", "l": 14, "r": 0, "s": 0}, {"t": "分かります", "l": 13, "r": 1, "s": 0}, {"t": "私も、この話好きです ほっこりしますね、", "l": 13, "r": 1, "s": 0}, {"t": "元気な赤ちゃん👶ですね 夜型なんですねかわいい💠", "l": 11, "r": 0, "s": 0}, {"t": "ありえるw", "l": 10, "r": 1, "s": 0}, {"t": "格闘家になるつもりだったのかと思った。ムキムキの大学生の赤ん坊はそうなんですね", "l": 8, "r": 0, "s": 0}, {"t": "草", "l": 7, "r": 1, "s": 0}, {"t": "ごめん😂爆笑しました。健康に育って何よりです😂", "l": 6, "r": 0, "s": 0}, {"t": "凄い赤ちゃん❤😂😂とっても可愛い💕😂😂❤", "l": 6, "r": 0, "s": 0}, {"t": "この話の猫ちゃんバージョンも有りますョね😺", "l": 6, "r": 0, "s": 0}, {"t": "まさか、あなたベテランの方ですか!?", "l": 5, "r": 1, "s": 0}, {"t": "よかったよかったよかったです お母様丈夫な赤ちゃんに恵まれました お幸せに〜❤❤❤❤❤❤❤❤❤❤❤❤✨🙏🙇🌈✨", "l": 5, "r": 0, "s": 0}, {"t": "長男どこに行ったんやろ", "l": 5, "r": 0, "s": 0}, {"t": "草超えてジャングル", "l": 4, "r": 1, "s": 0}, {"t": "筋肉は裏切らない！マッスルｩｩ！", "l": 4, "r": 1, "s": 0}, {"t": "😢", "l": 4, "r": 1, "s": 0}, {"t": "これ次男に話したらどんな表情するんだろう？", "l": 4, "r": 0, "s": 0}, {"t": "元気が、一番ですね。💪💪✨", "l": 4, "r": 0, "s": 0}, {"t": "運動選手になるために産まれてきたんだね。", "l": 3, "r": 0, "s": 0}, {"t": "武井壮さん、次男だから本人だったりして(笑)", "l": 3, "r": 1, "s": 0}, {"t": "ミオスタシ欠乏症ですよ。筋肉の成長を抑える成分が足りなくてムキムキになる分、消費カロリーが激しくて栄養失調になりがち。医師なら気付くはずですよ。", "l": 3, "r": 0, "s": 0}, {"t": "​ @前田kt ジャングルこえて ハエトリグサ", "l": 2, "r": 1, "s": 0}, {"t": "？？？ [ﾊﾟﾜｧｧｧｧｧｧｧｧ]", "l": 2, "r": 1, "s": 0}, {"t": "超絶的健康男児", "l": 2, "r": 0, "s": 0}, {"t": "人生2回目なのかな？ 両親を驚かさないように夜中に、身体鍛えてたのかも", "l": 2, "r": 0, "s": 0}, {"t": "次男最強やん", "l": 2, "r": 0, "s": 0}, {"t": "人生二周目勢か、、、", "l": 2, "r": 0, "s": 0}, {"t": "ウチの三男もそんな感じで、今中学生だけど、部活もしてないのにむきむきだから、そう言う感じの子は一定数いるんじゃ無いかな😅", "l": 2, "r": 0, "s": 0}, {"t": "少しでも動こうものなら旦那でもすぐ飛び起きるけど、ママで子供が起きて布団から出てって気づかない人とかいる？", "l": 2, "r": 0, "s": 0}, {"t": "スーパーアスリートは持って生まれたものがあったんですな。", "l": 2, "r": 0, "s": 0}, {"t": "脳ミソ🧠迄筋肉ではない事をお祈りします。😁", "l": 1, "r": 1, "s": 0}, {"t": "わかる。運動神経良い子は赤ちゃんの時から身体が締まってる。無い子はぷよぷよ筋肉がない😂", "l": 1, "r": 0, "s": 0}, {"t": "これがいわゆる転生系ってやつですな。今回は前回なかった筋肉をメインに鍛えて行ってますね。", "l": 1, "r": 0, "s": 0}, {"t": "よく動き、よく遊び、よく食べて、よく休め 亀仙流で草", "l": 1, "r": 0, "s": 0}, {"t": "これめちゃくちゃ微笑ましいけどめちゃくちゃ怖いよね親が見てないとこで怪我したらとか考えたら寝れない", "l": 1, "r": 0, "s": 0}, {"t": "すごくいい話。", "l": 1, "r": 0, "s": 0}, {"t": "筋肉ついても筋肉断裂するらしい", "l": 1, "r": 0, "s": 0}, {"t": "きっと人生2回目の赤ちゃん", "l": 1, "r": 0, "s": 0}, {"t": "元気でスクスク育ったのならば良かった❤潜在的に筋トレが出来る子だったとは驚きました😲😲😲", "l": 1, "r": 0, "s": 0}, {"t": "転生したから赤ん坊のうちに鍛えとるんよ", "l": 1, "r": 0, "s": 0}, {"t": "亀仙人の名言？", "l": 0, "r": 1, "s": 0}, {"t": "栴檀は双葉より芳し 赤子の頃からただ者ではない", "l": 0, "r": 0, "s": 0}, {"t": "本能なんですね🎉", "l": 0, "r": 0, "s": 0}, {"t": "本当に、こんな話あるのかしら？素敵ね！", "l": 0, "r": 0, "s": 0}, {"t": "オチが凄すぎて思わず笑ってしまった。", "l": 0, "r": 0, "s": 0}, {"t": "良い話じゃないかぁ", "l": 0, "r": 0, "s": 0}, {"t": "初見です！ （家用のタブレットでみたことがある。） このチャンネル初コメです！", "l": 0, "r": 0, "s": 0}, {"t": "筋肉の妖精だったか", "l": 0, "r": 0, "s": 0}, {"t": "マッシュが異世界転生したのか", "l": 0, "r": 0, "s": 0}, {"t": "ウチの娘もバキバキで筋肉質ですね😂女の子は、ふくよかなイメージだったのですが 抱っこしたらゴリゴリでよく男の子⁇て勘違いされましたよ。", "l": 0, "r": 0, "s": 0}, {"t": "赤ちゃんの時からスクワット！？スポーツ選手になる為に生まれてきた男だ！", "l": 0, "r": 0, "s": 0}, {"t": "明らかに、転生して2周目の人生をスタートさせてる。", "l": 0, "r": 0, "s": 0}, {"t": "行為も上手そう", "l": 0, "r": 0, "s": 0}, {"t": "OPいいな", "l": 0, "r": 0, "s": 0}, {"t": "…生まれ付きのアスリート体質だったんですね。😂😂", "l": 0, "r": 0, "s": 0}, {"t": "まさか猫以外でしかも赤ちゃんが夜中の大運動会を開催してるとは😂", "l": 0, "r": 0, "s": 0}, {"t": "前世が猫だったのかもしれませんね", "l": 0, "r": 0, "s": 0}, {"t": "よかったね。 しかしすごい「落ち」だね。まずは一安心。", "l": 0, "r": 0, "s": 0}, {"t": "あ、、平和、、", "l": 0, "r": 0, "s": 0}, {"t": "いい子やね｡ﾟ(ﾟﾉ∀｀ﾟ)ﾟ｡ｱﾋｬﾋｬ 将来大物になるな｡ﾟ(ﾟﾉ∀｀ﾟ)ﾟ｡ｱﾋｬﾋｬ", "l": 0, "r": 0, "s": 0}, {"t": "ムキムキ学生…なかやまきんに君じゃ…", "l": 0, "r": 0, "s": 0}, {"t": "此処までは覚えていないけど、小学校3年の時に前腕強化方法を考えたから、その前から筋トレ？遣っていたみたいだ。", "l": 0, "r": 0, "s": 0}, {"t": "前世アスリート確定 今世も同じ 怖い。", "l": 0, "r": 0, "s": 0}, {"t": "人生2回目のなろう系漫画や", "l": 0, "r": 0, "s": 0}, {"t": "元気な次男くん！ 体重が増えないと、心配ですよね(^^;) 私の子どもたちは、これほどアクティブではなかった。", "l": 0, "r": 0, "s": 0}], "n_total": 95}