{"ok": true, "comments": [{"t": "着いたのは警察署でした", "l": 576, "r": 0, "s": 0}, {"t": "バイクに、ヘルメット2つあったの凄いな。 ヤンキーの男性良かったねバイク乗れて 意味深なんかじゃないよ", "l": 334, "r": 0, "s": 0}, {"t": "青年はほんとにバイク🏍️好きだったんだね😢 イッチの優しさに感動だよ😢", "l": 134, "r": 0, "s": 0}, {"t": "やめろwwww", "l": 92, "r": 1, "s": 0}, {"t": "優しい兄ちゃん、カッコ良すぎる❤", "l": 82, "r": 0, "s": 0}, {"t": "義足でもスクーターには乗れるよね。 でも、やっぱそれでは満たされない自分が憧れてる大好きなバイクに乗りたいって気持ちはすごくわかる。", "l": 78, "r": 0, "s": 0}, {"t": "片手、片足で免許取り直して乗ってる人居るんですよね。", "l": 61, "r": 0, "s": 0}, {"t": "これは相手にとっては一生忘れられないやつ", "l": 52, "r": 0, "s": 0}, {"t": "自分のバイク（相棒）を褒められると嬉しいよね", "l": 39, "r": 0, "s": 0}, {"t": "こんなん、共に走り出さない訳ないだろ〜", "l": 35, "r": 0, "s": 0}, {"t": "イッチも義足の兄ちゃんもいい奴らだなぁ｡ 正月に最高にいい話を有難うございます｡", "l": 32, "r": 0, "s": 0}, {"t": "メット2個目どっからだしたん？ とか野暮なこと書きに来たら上がいた😅", "l": 31, "r": 1, "s": 0}, {"t": "涙で前が見えずに、二人乗りで事故ったのかと…", "l": 28, "r": 0, "s": 0}, {"t": "粋だな😢 いい話だよね😅", "l": 23, "r": 0, "s": 0}, {"t": "バイク好きはこんな風に通じ合うところがあるのが素敵な世界", "l": 15, "r": 0, "s": 0}, {"t": "感動返せ……笑", "l": 15, "r": 1, "s": 0}, {"t": "優しい人でよかったね", "l": 9, "r": 0, "s": 0}, {"t": "バットエンドなう✌️🥺", "l": 7, "r": 1, "s": 0}, {"t": "そうですね自分の友達は軍にいた時に片足無くしてずーとバイクに乗りたくて片足でも乗れるように 自分のバイク改造して今でも一緒にツーリング行く中です", "l": 7, "r": 1, "s": 0}, {"t": "ドライアイ悪化した", "l": 5, "r": 1, "s": 0}, {"t": "この後修理代は取りました", "l": 5, "r": 0, "s": 0}, {"t": "下半身不随でも乗れるように改造したバイクで サーキットを走った元レーサーの話を知っている 義足でも乗ることが出来るバイクあると思う", "l": 4, "r": 1, "s": 0}, {"t": "優しい 感動😢 拍手👏 泣きそう", "l": 4, "r": 0, "s": 0}, {"t": "このコメント100点💯はいえりりの負けーwww", "l": 3, "r": 1, "s": 0}, {"t": "@enqlnmieiobj 荒らしかと思ったわw", "l": 3, "r": 1, "s": 0}, {"t": "@小泉貴志-t6z 原付免許は持ってるんだから 警察に申告＞適性検査で、もしかしたらスクーターに限るとかの条件付になる可能性もある。ともあれ無申告は絶対NG。", "l": 3, "r": 1, "s": 0}, {"t": "いい話だな…（ウチの盆栽を見ながら", "l": 3, "r": 0, "s": 0}, {"t": "優しいなぁ…。", "l": 3, "r": 0, "s": 0}, {"t": "現実は非常である", "l": 3, "r": 1, "s": 0}, {"t": "可愛すぎ❤", "l": 3, "r": 0, "s": 0}, {"t": "スクーターなら予備入れてる人居るけどな", "l": 2, "r": 1, "s": 0}, {"t": "たまにタンデムシートの紐に引っ掛けてるか、ヘルメットロックのところに引っ掛けてるツーリングライダー多いよ、フルフェイス率高いし", "l": 2, "r": 1, "s": 0}, {"t": "最高かよ。目の前がボヤけてしょうがないわ。", "l": 2, "r": 0, "s": 0}, {"t": "憧れのバイクは乗れないかもしれないですが 片足義足でも訓練講習受ければ乗れます諦めてはいけません 『バイクに乗らない人は人生半分損している』とあるバイク乗りが言ってました", "l": 2, "r": 0, "s": 0}, {"t": "なんて律儀な子なんだ❤😊❤", "l": 2, "r": 0, "s": 0}, {"t": "クソすぎて草", "l": 2, "r": 1, "s": 0}, {"t": "このコメントのせいでなんか泣けてきたのが急に静まった 決して悪く言ってません", "l": 2, "r": 1, "s": 0}, {"t": "感動するけど最後不穏", "l": 2, "r": 0, "s": 0}, {"t": "だから？", "l": 1, "r": 1, "s": 0}, {"t": "​ @小泉貴志-t6z 引き起こしだけではダメです。 ８の字の引き回しも必須", "l": 1, "r": 1, "s": 0}, {"t": "@小泉貴志-t6z そもそも中型くらいなら義足でも引き起こすくらいできる 大型も頑張ればできる", "l": 1, "r": 1, "s": 0}, {"t": "@小泉貴志-t6z 義足のライダーに会ったことありますよ。 大型のスクーター乗ってました。 確か…T-MAXだったと記憶しています。", "l": 1, "r": 1, "s": 0}, {"t": "見てるだけで倒れないしメット２つも持ち歩くやついないというね", "l": 1, "r": 0, "s": 0}, {"t": "バイクはねぇ… 眺めて良し、乗って走らせてまた更に良しなんですよね。", "l": 1, "r": 0, "s": 0}, {"t": "隼かな いいよね隼バイク好きなら必ず憧れるバイク", "l": 1, "r": 0, "s": 0}, {"t": "この後、修理代請求しないまでを入れないと台無しになるよ(^-^;", "l": 1, "r": 0, "s": 0}, {"t": "ヘルメットも付いていてなぁ", "l": 1, "r": 1, "s": 0}, {"t": "今度は両足なくすと😂", "l": 1, "r": 1, "s": 0}, {"t": "ものすごくバットエンド", "l": 1, "r": 1, "s": 0}, {"t": "思ったわ", "l": 1, "r": 1, "s": 0}, {"t": "@たいやき-f9u その涙俺が笑いに変えてやるよ", "l": 1, "r": 1, "s": 0}, {"t": "無意識に言ったこともいいんだよな", "l": 1, "r": 0, "s": 0}, {"t": "その後目の前がぼやけた状態で走り事故って二人で星になりました", "l": 1, "r": 0, "s": 0}, {"t": "うぅ…あぶねえじゃねえかよおばかやろお…（泣）", "l": 1, "r": 0, "s": 0}, {"t": "早く見れた！いつも見てます！😊", "l": 1, "r": 0, "s": 0}, {"t": "感動してるとこゴメンよ。バイクは無事ではないよ？修理代って言ってんだ。", "l": 1, "r": 0, "s": 0}, {"t": "事故の伏線ハンパねぇ", "l": 1, "r": 0, "s": 0}, {"t": "ここから始まった漢同士の恋", "l": 1, "r": 0, "s": 0}, {"t": "最後目的地が交番だったドッキリじゃなくて良かった", "l": 1, "r": 0, "s": 0}, {"t": "隼！！", "l": 1, "r": 0, "s": 0}, {"t": "そして俺も義足になった", "l": 1, "r": 0, "s": 0}, {"t": "その後ホテルまで向かったとさおしまいおしまい", "l": 1, "r": 0, "s": 0}, {"t": "乗れないでしょ？ 引き起こし出来ないと免許取れないから。", "l": 0, "r": 1, "s": 0}, {"t": "イキすぎぃ！", "l": 0, "r": 1, "s": 0}, {"t": "​ @ボロネーぜ ご立派ァ！", "l": 0, "r": 1, "s": 0}, {"t": "まじでどこにでもいるやん", "l": 0, "r": 1, "s": 0}, {"t": "#ルイージみっけ", "l": 0, "r": 1, "s": 0}, {"t": "@Yuma-u3x 本人やめて欲しいって言ってるからこれからは見つけても言わないようにしてね！心の中でラッキーって思っとこ！", "l": 0, "r": 1, "s": 0}, {"t": "板抱いてもろて〜 最後板かあぁぁぁって言いながら、フェードアウトしてくの面白い😅", "l": 0, "r": 0, "s": 0}, {"t": "自分も14の時かなポケバイ乗ってたら当時新車で出たばっかりのXJR400乗ってるお兄さんが話しかけてくれて短い距離だったけど後ろに乗せてくれた。 16で免許取ってRZ250買ってたまに近所のバイク屋さん行ってたけど、アホなんでバイク屋さんに工具貸して下さいって言ったら店員さんが本当は工具は貸せないけど使ったらバレないようにここの花壇のところに置いといて。と言ってくれてお借りする時もあった。おっさんになってもずっとバイク乗ってるけど、良くして貰った事はずっと忘れないよね。", "l": 0, "r": 0, "s": 0}, {"t": "チェンジあるだけがバイクじゃ〜ないし👍夢は諦めないで😊", "l": 0, "r": 0, "s": 0}, {"t": "こういう事を想定して常にヘルメットもうひとつ搭載しているなんて 本当にものすごく感動です", "l": 0, "r": 0, "s": 0}, {"t": "バイク乗りはニケツするために大体2個持ってる", "l": 0, "r": 1, "s": 0}, {"t": "このｼﾘｰｽﾞいい人い過ぎだなぁ😊", "l": 0, "r": 0, "s": 0}, {"t": "いい仲間できて良かったですね。", "l": 0, "r": 0, "s": 0}, {"t": "信号がわからないくらい目の前がぼやけてるって、車のヘッドライト迫ってきとる😮", "l": 0, "r": 0, "s": 0}, {"t": "相手を刺青陽キャに見立てることで、自分の自己肯定感を上げる高等テクニック。 覚えときな！", "l": 0, "r": 0, "s": 0}, {"t": "泣きながら運転は危ないぞ！今度は2人とも笑顔で乗ってな！", "l": 0, "r": 0, "s": 0}, {"t": "涙がバイクの急加速並みに走行しやがるぜ。アクセル全開ブンブンブーン‼️( *｀ω´)", "l": 0, "r": 0, "s": 0}, {"t": "アドレナリンが出ながら事故ったヤツは戻ってくるの法則。", "l": 0, "r": 0, "s": 0}], "n_total": 111}