{"ok": true, "comments": [{"t": "捨てる神あれば拾う神あり。 別れた後だからこそ 気付く事もある。 親友との絆いつまでも大切にね。", "l": 6600, "r": 0, "s": 0}, {"t": "一生ものの親友だね 親友ってなかなか望んでも出会えない貴重な人だよ", "l": 3400, "r": 0, "s": 0}, {"t": "親友さんが最高すぎ", "l": 1500, "r": 0, "s": 0}, {"t": "持つべきは友ですね。 利害関係ないし、救われる事ある。 親友、良いよね。", "l": 522, "r": 0, "s": 0}, {"t": "辛い事があってすぐでも、誰かの為に犠牲を払えるカッコイイ奴じゃん", "l": 476, "r": 0, "s": 0}, {"t": "無くした物が有れば得るものも有りましたね。 親友だな。泣けるぜ", "l": 335, "r": 0, "s": 0}, {"t": "善意だらけのすんごい、いい話！ 腐った政治の話題や事件が溢れてるけど救われた気分になるよ", "l": 244, "r": 0, "s": 0}, {"t": "親友って本当に大事ですよね。", "l": 199, "r": 0, "s": 0}, {"t": "最高の親友です✨親友さんとずっと仲良しでいてね。親友さん大切にしてあげてね🎉", "l": 143, "r": 0, "s": 0}, {"t": "正しく親友…てか真友😊 うらやましい🤣", "l": 125, "r": 0, "s": 0}, {"t": "ホントしあわせ者。オレと一緒に喜んでくれる親友最高です。裏山しいな♪", "l": 101, "r": 0, "s": 0}, {"t": "数十年前の友人がそんな感じな男だった。 景気のいい時は寄って来るけど駄目な時はさっと逃げる様な人ではなくどんな時でも付き合ってくれる友人。 人生いい友人との出会いがあるかないかで大きく違うと思う。", "l": 98, "r": 0, "s": 0}, {"t": "一緒にいるだけで前向きになって出来事に感謝が出来るのは真の親友だよな。 いい話だった！", "l": 76, "r": 0, "s": 0}, {"t": "良い奴だなぁ‼️‼️親友君‼️‼️", "l": 65, "r": 0, "s": 0}, {"t": "本当に良かったね🥹交番で聞いてみてナイスだった😭 スマホも無事に持ち主の元に届いているといいな🥺✨", "l": 63, "r": 0, "s": 0}, {"t": "親友もすごく良い人だけど、そもそも本人も素敵な人なんだろうね", "l": 50, "r": 0, "s": 0}, {"t": "いい言葉🤭", "l": 41, "r": 1, "s": 0}, {"t": "良い友だね。まさに親友だね。", "l": 34, "r": 0, "s": 0}, {"t": "いい。すごくいい。", "l": 34, "r": 0, "s": 0}, {"t": "禍福は糾える縄の如し、か。 あと、自分の調子がいい時に近寄って来る者なんかより、悪いときに寄り添ってくれる人が本当に大切だと教えてくれますね。", "l": 26, "r": 0, "s": 0}, {"t": "女は幾らでも替えはある、良いお友達だよ、頑張って次にGO❕", "l": 22, "r": 0, "s": 0}, {"t": "小さな幸せに気づける人は大きな幸せを手にするね😊", "l": 21, "r": 0, "s": 0}, {"t": "親友がいるって羨ましい。彼女はすぐできても、親友は人生でひとりでも得られたら幸せです。", "l": 20, "r": 0, "s": 0}, {"t": "スマホの落とし主が財布届けてくれた人、ってオチだと予想した。 読み過ぎだった。", "l": 15, "r": 1, "s": 0}, {"t": "この人、いい思い出ができたね！ 失恋した相手は縁がなかったんだから、いつかは離れたと思うよ 素晴らしい親友に感謝だよね", "l": 15, "r": 0, "s": 0}, {"t": "困ってる時に寄り添ってくれる大事な友人。彼女はまた作ればいいけど親友は唯一無二の存在。", "l": 14, "r": 0, "s": 0}, {"t": "親友は大切な存在 貴方のような人が羨ましい", "l": 13, "r": 0, "s": 0}, {"t": "人助ければ我が身助かる。だね！ 良い親友がいて良かったですね！ やっぱ持つものは親友やろ！", "l": 12, "r": 0, "s": 0}, {"t": "奇跡の夜 でも親友が一番だね", "l": 11, "r": 1, "s": 0}, {"t": "スマホを落としたのが財布を拾ってくれた人だった", "l": 11, "r": 0, "s": 0}, {"t": "良い友人", "l": 9, "r": 0, "s": 0}, {"t": "親友呼べる人は生涯何人できるか🖐️ 彼女はまた縁あれば出来ますよ！ 色々気付ける時があって良かったですね👍", "l": 8, "r": 1, "s": 0}, {"t": "うちの拾う神はどこに行っちゃったんだろう", "l": 7, "r": 1, "s": 0}, {"t": "悲しい時にいてくれる友人は大切やねぇ……振られたのも…次の出逢いがあるから…きっと素敵な人かあらわれるね…", "l": 7, "r": 1, "s": 0}, {"t": "2人でもこういうノリができる友達ってまじで大切よな", "l": 6, "r": 0, "s": 0}, {"t": "お前もたぶん、同じくらいいいヤツなんやぞ", "l": 6, "r": 0, "s": 0}, {"t": "そのコメントを書いてるあなたがとても素敵ですよ。", "l": 5, "r": 1, "s": 0}, {"t": "友達って家族とか恋人と違って 本当に恵まれて良かったって思える人が何人もいるのは 最高に幸せですよね", "l": 5, "r": 0, "s": 0}, {"t": "ぼっちのわたしが言うのもなんだけど、辛い時、困ってる時、そばにいてくれる人は本物、だからその友情がずっと続きますように。 相手が辛い時苦しい時かけつけたのに、わたしが辛い時苦しい時には来ない人の為に時間を割くのやめたらぼっちになった^ ^ でも割といい感じ♪", "l": 5, "r": 0, "s": 0}, {"t": "いい話ですね 心が温まりました☺️☺️☺️☺️☺️", "l": 5, "r": 0, "s": 0}, {"t": "この話の続き 後日、主人公宛に電話があった。 それは、警察からで、「携帯の持ち主が見つかって感謝がしたいと、、、」と 言った。 主人公が交番につくと、そこには別れた彼女が、 彼女は顔をうつむかせ、主人公も同様した。 でも、彼女が「ありがとう」と小声で言った。主人公は、彼女と出た。 そして、彼女は言った。 「昨日、財布なくしたでしょ？」 昨日、財布を届けたのは彼女だった。 二人は顔を見合せ笑った。 完", "l": 4, "r": 1, "s": 0}, {"t": "財布拾ったのが彼女で落ちてたスマホの持ち主も彼女だったらガチの奇跡だったな", "l": 4, "r": 0, "s": 0}, {"t": "いい親友をお持ちですね。一生の友になさって下さい😊", "l": 4, "r": 0, "s": 0}, {"t": "捨てる神あれば、拾う神あり 目まぐるしい一日でしたね。😂", "l": 4, "r": 0, "s": 0}, {"t": "よかったですね‼️ 親友を大切になさってくださいね。 友達がいると言うことは、心の財産です。m(_ _)m", "l": 4, "r": 0, "s": 0}, {"t": "彼女はアレだったけど．彼s、、、親友は最高だな", "l": 3, "r": 0, "s": 0}, {"t": "素敵な話だ。感動した！", "l": 3, "r": 0, "s": 0}, {"t": "当日は寝ながら仕事。", "l": 3, "r": 0, "s": 0}, {"t": "携帯落とした人が財布届けてくれた人で めっちゃ美人やったら運命感じるしかない", "l": 2, "r": 0, "s": 0}, {"t": "明日仕事なのにカラオケオールはダルすぎるやろ", "l": 2, "r": 0, "s": 0}, {"t": "サイフみつかってよかったね ❤🎉", "l": 2, "r": 0, "s": 0}, {"t": "そして自分たちが届けたスマホの落とし主が、財布を届けてくれた人だった…ってオチかと思ってた…", "l": 2, "r": 0, "s": 0}, {"t": "拾ったスマホが女性のもので、お礼しにきた女性が彼女になった… まで妄想したのにそこまで届いていなかった。", "l": 1, "r": 0, "s": 0}, {"t": "スマホ落とした人が財布を届けてくれたのでしょう。", "l": 1, "r": 0, "s": 0}, {"t": "スマホ財布届けてくれた人のだったらおもろい", "l": 1, "r": 0, "s": 0}, {"t": "善因善果っていうし普段からほんとにいい人なんだろうな。だから素敵な友人にも恵まれてる。私もそうあれるように心がけよう", "l": 1, "r": 0, "s": 0}, {"t": "こういうノリをしたいし、 してあげたいんだけどね、 次の日のこととか、身なりとか、 臭いとか考えると オッサンには無理なのよ、オールなんて、 もう…", "l": 1, "r": 0, "s": 0}, {"t": "若い頃は戻らないから財布より大事にね。", "l": 1, "r": 0, "s": 0}, {"t": "もう、その親友と生涯いっしょに暮らしたら？ｗ", "l": 1, "r": 0, "s": 0}, {"t": "元カノと別れた時に親友が教えてくれた。彼女はいなくなっても、俺たちはいなくならない！その言葉にあの時は凄く救われた。", "l": 1, "r": 0, "s": 0}, {"t": "いいねえ！ こういうオールってあるよ。翌日の仕事はツライけど、狙って作れる思い出じゃない。ポジティブに生きよう！", "l": 1, "r": 0, "s": 0}, {"t": "イージーカムイージーゴー", "l": 0, "r": 1, "s": 0}, {"t": "良い友や", "l": 0, "r": 0, "s": 0}, {"t": "若い頃は、モテたかったり地位や権力が欲しかったりとか色々あったけど 50歳過ぎたら「友達(家族も含む)」と「健康」が何より大事だなと思うようになった。", "l": 0, "r": 0, "s": 0}, {"t": "このコメまじ好き", "l": 0, "r": 1, "s": 0}, {"t": "自分の 不幸を笑うのは他人 不幸を嘆いてくれるのは友達 不幸のドブに一緒にハマり助けてくれるのは親友", "l": 0, "r": 0, "s": 0}, {"t": "百人の友達を作るのも良いけれど、一人の親友を作れたこのお二人は、最高の二人ですね。😊", "l": 0, "r": 0, "s": 0}, {"t": "人は 優しくて 温かい。", "l": 0, "r": 0, "s": 0}, {"t": "効率悪い奴らだな 仕事もできないモテもしない 改めて欲しいことばかりある内容でした", "l": 0, "r": 0, "s": 0}, {"t": "いい友達だな もうオールで仕事する体力のない私には、そっちも羨ましい。", "l": 0, "r": 0, "s": 0}, {"t": "笑って話せる親友が居ることが最高の奇跡😂", "l": 0, "r": 0, "s": 0}, {"t": "日本は大抵届けてくれるよな。全員じゃなくて一部の人だが、その一部が多い国。そしていい友達を持ったな！", "l": 0, "r": 0, "s": 0}, {"t": "最高の友人🎉です✨ね〜将来の友人だぁ～❤", "l": 0, "r": 0, "s": 0}, {"t": "彼女いなくても十分幸せ", "l": 0, "r": 0, "s": 0}, {"t": "友達とオールして 朝から仕事すると確かにしんどい。 でも休憩中に「バリしんどい」とかの報告し合うとまあアイツも頑張ってるしみたいな感じで乗り切れんのよな。", "l": 0, "r": 0, "s": 0}, {"t": "凄く分かる！親友って困ってる時でもノリでやってる感出してくれるよね。 俺もそうするし。", "l": 0, "r": 0, "s": 0}, {"t": "こういう話を見ると、やはり男同士の方が楽しいし、安心できるのだとも思う。", "l": 0, "r": 0, "s": 0}, {"t": "いい話😢❤彼女探すより親友探す方がだいぶ難しい気がする…", "l": 0, "r": 0, "s": 0}, {"t": "人生にこんな親友がいれば他に何もいらないよな。", "l": 0, "r": 0, "s": 0}, {"t": "親友聖人すぎる", "l": 0, "r": 0, "s": 0}], "n_total": 90}