{"ok": true, "comments": [{"t": "御両親があなたを見守っているのだと思いました。よく頑張ってきたね。大切な人と幸せに過ごして下さい。あなた達の幸せを願います。", "l": 823, "r": 0, "s": 0}, {"t": "いい出会いがあってよかったですね☺", "l": 661, "r": 0, "s": 0}, {"t": "見かけによらず優しい方なんですね☺️✨その彼氏さん,大切にしてくださいね✨", "l": 382, "r": 0, "s": 0}, {"t": "お互い同じ経験をしている同士だからこそわかりあえたのかもしれないですね。", "l": 93, "r": 0, "s": 0}, {"t": "素敵なシリーズですよね、このイラスト系の馴れ初め話 この2人には幸せになってほしい😢", "l": 88, "r": 0, "s": 0}, {"t": "素敵な出会いだったね🥺✨", "l": 87, "r": 0, "s": 0}, {"t": "最初怖そうに見えたのも、その男性なりに災害の辛い記憶やサバイバーズギルトと戦ってて、周囲に心を閉ざしてたのかも でも本来は人を心から気遣える素敵な男性だったんですね", "l": 64, "r": 0, "s": 0}, {"t": "自分もパニック障害持ちだからわかるけどまじで動けんのよ。。。手足も冷えて動かなくて「ﾀﾋんじゃうかも」って不安で倒れ込んじゃうからすごく救われたと思う。", "l": 27, "r": 0, "s": 0}, {"t": "過呼吸同じですね。 家族との思いが多くあるなら、家族との思い出を思い出しながらさすったりするといいよ！", "l": 26, "r": 0, "s": 0}, {"t": "素敵😊", "l": 26, "r": 0, "s": 0}, {"t": "運命的な出会いがうらやましいです。。。💧", "l": 25, "r": 0, "s": 0}, {"t": "良い人で良かったね！😊", "l": 25, "r": 0, "s": 0}, {"t": "人は見かけだけじゃないってことですね😊いい人に巡り会えてよかったですね😊", "l": 23, "r": 0, "s": 0}, {"t": "この絵すきなんよね", "l": 21, "r": 0, "s": 0}, {"t": "良い出逢いだったのかな… お幸せに…", "l": 13, "r": 0, "s": 0}, {"t": "こういう話って経験者しかわからないですよね。大切な人巡り会えてよかったですね。", "l": 9, "r": 0, "s": 0}, {"t": "😭😭😭ええ話やなぁ😭😭😭", "l": 9, "r": 0, "s": 0}, {"t": "恋の名言集やん", "l": 7, "r": 0, "s": 0}, {"t": "運命の相手か", "l": 7, "r": 0, "s": 0}, {"t": "お互いを思い合えるって素晴らしい 羨ましいです 末永くお幸せに", "l": 6, "r": 0, "s": 0}, {"t": "@林田周三-s4h 何言ってんの？", "l": 3, "r": 1, "s": 0}, {"t": "​ @ゆゆ_701 人生万事が塞翁が馬、災い転じて福となす？とか、すみません🙏", "l": 3, "r": 1, "s": 0}, {"t": "そんなドラマみたいな出会い方が現実にあるといいね", "l": 3, "r": 0, "s": 0}, {"t": "大きな困難や辛い経験も、アナタを理解して、一緒に歩いてくれる人が居たら、本当に心強く生きて行けますね。 幸せになって下さい👦❤👧", "l": 3, "r": 0, "s": 0}, {"t": "いらすとやでこんな動きできるの神", "l": 3, "r": 0, "s": 0}, {"t": "なぜかスマホの下の方を見てしまう", "l": 3, "r": 0, "s": 0}, {"t": "​ @ゆゆ_701 塞翁が馬とはこの話のように人生には予想できない出会いがあるということです", "l": 2, "r": 1, "s": 0}, {"t": "ご両親が粋な出会いを🥰", "l": 2, "r": 0, "s": 0}, {"t": "こんな所に運命の出会いってあるんですね😊", "l": 2, "r": 0, "s": 0}, {"t": "袋被ってれば楽になるよ", "l": 2, "r": 0, "s": 0}, {"t": "☝人生いろいろ？いや、「🐴塞翁が馬🎉」だな😅", "l": 1, "r": 1, "s": 0}, {"t": "地震はトラウマになるね😢ちょっとの揺れでも心臓バクバクするし 地震の度に出会ったきっかけを思い出せるのは良いのかも", "l": 1, "r": 0, "s": 0}, {"t": "同じ心の傷を追う人が傍にいて寄り添ってくれた人が彼氏になって良かったね😊たまたま運の出会いになってくれた方が親切な人で良かったっておもう😊", "l": 1, "r": 0, "s": 0}, {"t": "素敵ですね😊", "l": 1, "r": 0, "s": 0}, {"t": "人って外見じゃなくて、やっぱ 中身が大事なんだなって思った なんていい話なんだ", "l": 1, "r": 0, "s": 0}, {"t": "帰宅て事は1階から乗り登ってたんだよね！ せっかく最寄りまで登ってたのにこの男わざわざ1階まで戻ったのか？ 何階か分からないにしても少なくともその階より上だって分かったろうに！ そしてまたエレベーター乗ったんかい？ エレベーター止まった経験後に？ と優しい男との出会いより気になった😅", "l": 1, "r": 0, "s": 0}, {"t": "普通の人ならほっとかないよね。", "l": 1, "r": 0, "s": 0}, {"t": "❤😇👍", "l": 1, "r": 0, "s": 0}, {"t": "コウジね…もぉほんとずっと言ってるんだけど…… チノちゃんって……この世界でいちばん可愛いの！！！！！！☕️🐇💙🫧☁️✨ 声はね……透明で冷たそうなのに、奥の奥でぬくもりがあって……聞いた瞬間、ハートがキュンってなるの……！💘💘💘 『ラビットハウスへようこそ』って言われた瞬間に魂ごと溶けた……無理……好き……🫠💕 仕草もやばいの。お盆を持ってトテトテ歩く足音、ちっちゃな指でカップをもつ姿、ぜんぶが繊細な宝石みたいで……💎🩵✨ 口数少ないのに、言葉のひとつひとつが重たくて、でもふわふわしてて…… 『うるさいです』←ご褒美ですありがとう！！！！！！😭🤍🙇🙇🙇", "l": 0, "r": 1, "s": 0}, {"t": "いい人ですね！そのままゴールインして欲しい", "l": 0, "r": 0, "s": 0}, {"t": "やっぱり人は、見た目が怖くても心は優しいんだなぁー 人は、見掛けによらないって事だな", "l": 0, "r": 0, "s": 0}, {"t": "一番弱い辛い部分をわかってくれる人はそうはいませんよね お幸せに😊❤", "l": 0, "r": 0, "s": 0}, {"t": "いいはなし。 お幸せに。", "l": 0, "r": 0, "s": 0}, {"t": "巡り合わせだね。 大事に、大事にね。", "l": 0, "r": 0, "s": 0}, {"t": "勇気を出して良かった", "l": 0, "r": 0, "s": 0}, {"t": "同じ過去の経験をしたからこそ繋ぎ止められた出会いか…😮", "l": 0, "r": 0, "s": 0}, {"t": "親切な、男性ですネ☺️ お互いに､幸せになって下さい❣️", "l": 0, "r": 0, "s": 0}, {"t": "被災者の人にとっては一生トラウマだよな...", "l": 0, "r": 0, "s": 0}, {"t": "うえーい🙌 期待通りの惚気だー😀✨", "l": 0, "r": 0, "s": 0}, {"t": "ええ話や❤", "l": 0, "r": 0, "s": 0}, {"t": "人を見た目で判断してはいけないね", "l": 0, "r": 0, "s": 0}, {"t": "幸せにおなり。", "l": 0, "r": 0, "s": 0}, {"t": "出会いは別として、このようなトラウマもつ方は多いんだろうな😢", "l": 0, "r": 0, "s": 0}, {"t": "地震で知り合ったから、心が揺れたんですね。チャン、チャン", "l": 0, "r": 0, "s": 0}, {"t": "何でエレベータ乗ったのに一階までおんぶで行ったんだよww 想像したらシュールで割ったわ", "l": 0, "r": 0, "s": 0}, {"t": "２人とも相手がいなかったなんて奇跡", "l": 0, "r": 0, "s": 0}, {"t": "なんかおおかみこどもの雨と雪を連想してしまったのはなんでだろうか", "l": 0, "r": 0, "s": 0}, {"t": "赤い糸ってどこに落ちてるのか分かりませんね😊 ステキ👏👏 やはり中身大事😊 見た目だけで決めてる彼女、彼氏いませんか? そういう人間は頭のネジが外れてると思ってます。", "l": 0, "r": 0, "s": 0}, {"t": "家賃半額になってよかったね", "l": 0, "r": 0, "s": 0}, {"t": "良かったね😊", "l": 0, "r": 0, "s": 0}, {"t": "そう言う過去があるなら、エレベーターに乗らなくてもいい階に住んだ方が良いのかもね。", "l": 0, "r": 0, "s": 0}, {"t": "全然話かんけいないけど すげー語り手の女性の絵がミサトさんにみえるw", "l": 0, "r": 0, "s": 0}, {"t": "経験しましたと被害にあいましたは違うよな。大震災地域のほんとの端のほうでちょっと揺れた程度で俺はあの震災を経験したんだ！みたいな人かなり多い。", "l": 0, "r": 0, "s": 0}, {"t": "全部受け止める？夜は君が受け止めるんでしょ❤", "l": 0, "r": 0, "s": 0}, {"t": "良かったね、逆に変な人ならと思うと😱😱", "l": 0, "r": 0, "s": 0}, {"t": "EVに閉じ込められて ぐふふ", "l": 0, "r": 0, "s": 0}, {"t": "これで見捨てたら後味悪いぜ！", "l": 0, "r": 0, "s": 1}, {"t": "吊り橋効果やん", "l": 0, "r": 0, "s": 0}, {"t": "ロン毛のちょい髭がある男性、僕も好きなんだよなぁァ...。((", "l": 0, "r": 0, "s": 0}, {"t": "？？？にゃんこでキャスリィとイザナギ？ってやつでたからXPにしといたぜ！", "l": 0, "r": 0, "s": 0}, {"t": "イッチ見た目で判断するとかヤバい奴だな", "l": 0, "r": 0, "s": 0}, {"t": "これは…吊り橋効果でいいのか？ 特別なケースなのか？", "l": 0, "r": 0, "s": 0}, {"t": "部屋を通り越して公園に連れて行く男の意図が不明だし、いくらパニックになってるとは言え知らない男におんぶされて夜中の公園に連れて行かれる事に抵抗がないのは危機感が無さ過ぎる。 世の女性たちはロマンを感じる前に一旦リアルに想像して欲しい、この状況を。", "l": 0, "r": 0, "s": 0}, {"t": "東日本大震災ですか？私も話を聞いてずっと震えてた", "l": 0, "r": 0, "s": 0}, {"t": "そんな症状があったら、一階に住んだほうがいいですよ。", "l": 0, "r": 0, "s": 0}, {"t": "関東大震災ってやばかったもんな", "l": 0, "r": 0, "s": 0}, {"t": "このフリーなんなん？", "l": 0, "r": 0, "s": 0}, {"t": "ロン毛の人が、シャフスにしか見えない、 (伝わる人には伝わる)", "l": 0, "r": 0, "s": 0}, {"t": "こういうのを求めてる", "l": 0, "r": 0, "s": 0}, {"t": "安藤優子？", "l": 0, "r": 0, "s": 0}], "n_total": 85}